composabl_ray/runtime.cpython-39-darwin.so
composabl_ray/main.cpython-39-darwin.so
composabl_ray/__init__.cpython-39-darwin.so
composabl_ray/skill_demo.cpython-39-darwin.so
composabl_ray/training_callbacks.cpython-39-darwin.so
composabl_ray/env/env_composabl_selector.cpython-39-darwin.so
composabl_ray/env/env_mgr.cpython-39-darwin.so
composabl_ray/env/__init__.cpython-39-darwin.so
composabl_ray/env/env_composabl.cpython-39-darwin.so
composabl_ray/env/env_config.cpython-39-darwin.so
composabl_ray/processors/controller_processor.cpython-39-darwin.so
composabl_ray/processors/selector_processor.cpython-39-darwin.so
composabl_ray/processors/space_utils.cpython-39-darwin.so
composabl_ray/processors/base_skill_processor.cpython-39-darwin.so
composabl_ray/model/skill_model.cpython-39-darwin.so
composabl_ray/model/__init__.cpython-39-darwin.so
composabl_ray/actor/actor.cpython-39-darwin.so
composabl_ray/actor/__init__.cpython-39-darwin.so
composabl_ray/trainer/__init__.cpython-39-darwin.so
composabl_ray/trainer/skill_trainer.cpython-39-darwin.so
composabl_ray/trainer/skill_trainer_base.cpython-39-darwin.so
composabl_ray/trainer/skill_trainer_selector.cpython-39-darwin.so
composabl_ray-0.4.2.dist-info/RECORD
composabl_ray-0.4.2.dist-info/WHEEL
composabl_ray-0.4.2.dist-info/top_level.txt
composabl_ray-0.4.2.dist-info/METADATA
