Metadata-Version: 2.1
Name: composabl-ray
Version: 0.4.2
Summary: a distributed runtime to be able to train agents across a cluster of machines
Author-email: Xavier Geerinck <xavier@composabl.io>, Hunter Park <hunter@composabl.io>
Requires-Python: >=3.8
Requires-Dist: composabl-core >=0.4.2
Requires-Dist: networkx ==3.1
Requires-Dist: dapr ==1.10.0
Requires-Dist: docker ==6.1.3
Requires-Dist: kubernetes ==27.2.0
Requires-Dist: pytest-asyncio ==0.21.0
Requires-Dist: ray[rllib] ==2.8.0
Requires-Dist: urllib3 ==1.26.12
Requires-Dist: torch ==2.0.0
